xintegrator/__init__.py
xintegrator/integration.py
xintegrator/sentiment_analyzer.py
xintegrator-4.3.0.dist-info/METADATA
xintegrator-4.3.0.dist-info/WHEEL
xintegrator-4.3.0.dist-info/RECORD
