Metadata-Version: 2.1
Name: xintegrator
Version: 4.3.0
Summary: xintegrator is a Python wrapper for integrating with the X (formerly Twitter) api
Author: Niklas Alexander Shern
Author-email: nshern@protonmail.com
Requires-Python: >=3.11,<4.0
Classifier: Programming Language :: Python :: 3
Classifier: Programming Language :: Python :: 3.11
Requires-Dist: pandas (>=2.0.3,<3.0.0)
Requires-Dist: plotly (>=5.16.1,<6.0.0)
Requires-Dist: requests (>=2.31.0,<3.0.0)
Requires-Dist: streamlit (>=1.26.0,<2.0.0)
